[
  {
    "range": {
      "worksheetId": "{5D160305-F8C9-4D69-B6C0-965E97D71DB2}",
      "top": 1,
      "left": 1,
      "bottom": 501,
      "right": 11
    },
    "interpretations": [
      {
        "confidence": 1,
        "location": {
          "worksheetId": "{5D160305-F8C9-4D69-B6C0-965E97D71DB2}",
          "top": 1,
          "bottom": 501,
          "left": 1,
          "right": 11
        },
        "orientation": "columnMajor",
        "headerRowCount": 1,
        "headerColumnCount": 0,
        "fields": [
          {
            "classification": "dimension",
            "aggregations": [],
            "headerReferences": [],
            "isTextual": false
          },
          {
            "classification": "dimension",
            "aggregations": [],
            "headerReferences": [],
            "isTextual": false
          },
          {
            "classification": "measure",
            "aggregations": [
              "average"
            ],
            "headerReferences": [],
            "isTextual": false
          },
          {
            "classification": "measure",
            "aggregations": [
              "sum"
            ],
            "headerReferences": [],
            "isTextual": false
          },
          {
            "classification": "measure",
            "aggregations": [
              "average"
            ],
            "headerReferences": [],
            "isTextual": false
          },
          {
            "classification": "measure",
            "aggregations": [
              "sum"
            ],
            "headerReferences": [],
            "isTextual": false
          },
          {
            "classification": "measure",
            "aggregations": [
              "average"
            ],
            "headerReferences": [],
            "isTextual": false
          },
          {
            "classification": "measure",
            "aggregations": [
              "average"
            ],
            "headerReferences": [],
            "isTextual": false
          },
          {
            "classification": "measure",
            "aggregations": [
              "average"
            ],
            "headerReferences": [],
            "isTextual": false
          },
          {
            "classification": "measure",
            "aggregations": [
              "average"
            ],
            "headerReferences": [],
            "isTextual": false
          },
          {
            "classification": "dimension",
            "aggregations": [],
            "headerReferences": [],
            "isTextual": false
          }
        ],
        "headerNames": [
          "\"Country\"",
          "\"Year\"",
          "\"Average_Monthly_Income\"",
          "\"Cost_of_Living\"",
          "\"Housing_Cost_Percentage\"",
          "\"Tax_Rate\"",
          "\"Savings_Percentage\"",
          "\"Healthcare_Cost_Percentage\"",
          "\"Education_Cost_Percentage\"",
          "\"Transportation_Cost_Percentage\"",
          "\"Region\""
        ],
        "sampleCellData": [
          {
            "row": 1,
            "column": 1,
            "displayText": "Country",
            "rawValueJson": "\"Country\"",
            "numberFormat": "General"
          },
          {
            "row": 1,
            "column": 2,
            "displayText": "Year",
            "rawValueJson": "\"Year\"",
            "numberFormat": "General"
          },
          {
            "row": 1,
            "column": 3,
            "displayText": "Average_Monthly_Income",
            "rawValueJson": "\"Average_Monthly_Income\"",
            "numberFormat": "General"
          },
          {
            "row": 1,
            "column": 4,
            "displayText": "Cost_of_Living",
            "rawValueJson": "\"Cost_of_Living\"",
            "numberFormat": "General"
          },
          {
            "row": 1,
            "column": 5,
            "displayText": "Housing_Cost_Percentage",
            "rawValueJson": "\"Housing_Cost_Percentage\"",
            "numberFormat": "General"
          },
          {
            "row": 1,
            "column": 6,
            "displayText": "Tax_Rate",
            "rawValueJson": "\"Tax_Rate\"",
            "numberFormat": "General"
          },
          {
            "row": 1,
            "column": 7,
            "displayText": "Savings_Percentage",
            "rawValueJson": "\"Savings_Percentage\"",
            "numberFormat": "General"
          },
          {
            "row": 1,
            "column": 8,
            "displayText": "Healthcare_Cost_Percentage",
            "rawValueJson": "\"Healthcare_Cost_Percentage\"",
            "numberFormat": "General"
          },
          {
            "row": 1,
            "column": 9,
            "displayText": "Education_Cost_Percentage",
            "rawValueJson": "\"Education_Cost_Percentage\"",
            "numberFormat": "General"
          },
          {
            "row": 1,
            "column": 10,
            "displayText": "Transportation_Cost_Percentage",
            "rawValueJson": "\"Transportation_Cost_Percentage\"",
            "numberFormat": "General"
          },
          {
            "row": 1,
            "column": 11,
            "displayText": "Region",
            "rawValueJson": "\"Region\"",
            "numberFormat": "General"
          },
          {
            "row": 2,
            "column": 1,
            "displayText": "Australia",
            "rawValueJson": "\"Australia\"",
            "numberFormat": "General"
          },
          {
            "row": 2,
            "column": 2,
            "displayText": "2013",
            "rawValueJson": "2013",
            "numberFormat": "General"
          },
          {
            "row": 2,
            "column": 3,
            "displayText": "3483.92",
            "rawValueJson": "3483.92",
            "numberFormat": "General"
          },
          {
            "row": 2,
            "column": 4,
            "displayText": "1106.07",
            "rawValueJson": "1106.07",
            "numberFormat": "General"
          },
          {
            "row": 2,
            "column": 5,
            "displayText": "32.09",
            "rawValueJson": "32.09",
            "numberFormat": "General"
          },
          {
            "row": 2,
            "column": 6,
            "displayText": "27.5",
            "rawValueJson": "27.5",
            "numberFormat": "General"
          },
          {
            "row": 2,
            "column": 7,
            "displayText": "1.74",
            "rawValueJson": "1.74",
            "numberFormat": "General"
          },
          {
            "row": 2,
            "column": 8,
            "displayText": "18.23",
            "rawValueJson": "18.23",
            "numberFormat": "General"
          },
          {
            "row": 2,
            "column": 9,
            "displayText": "6.94",
            "rawValueJson": "6.94",
            "numberFormat": "General"
          },
          {
            "row": 2,
            "column": 10,
            "displayText": "17.19",
            "rawValueJson": "17.19",
            "numberFormat": "General"
          },
          {
            "row": 2,
            "column": 11,
            "displayText": "Oceania",
            "rawValueJson": "\"Oceania\"",
            "numberFormat": "General"
          },
          {
            "row": 3,
            "column": 1,
            "displayText": "India",
            "rawValueJson": "\"India\"",
            "numberFormat": "General"
          },
          {
            "row": 3,
            "column": 2,
            "displayText": "2019",
            "rawValueJson": "2019",
            "numberFormat": "General"
          },
          {
            "row": 3,
            "column": 3,
            "displayText": "7771.03",
            "rawValueJson": "7771.03",
            "numberFormat": "General"
          },
          {
            "row": 3,
            "column": 4,
            "displayText": "5422.78",
            "rawValueJson": "5422.78",
            "numberFormat": "General"
          },
          {
            "row": 3,
            "column": 5,
            "displayText": "25.21",
            "rawValueJson": "25.21",
            "numberFormat": "General"
          },
          {
            "row": 3,
            "column": 6,
            "displayText": "29.3",
            "rawValueJson": "29.3",
            "numberFormat": "General"
          },
          {
            "row": 3,
            "column": 7,
            "displayText": "3.35",
            "rawValueJson": "3.35",
            "numberFormat": "General"
          },
          {
            "row": 3,
            "column": 8,
            "displayText": "17.21",
            "rawValueJson": "17.21",
            "numberFormat": "General"
          },
          {
            "row": 3,
            "column": 9,
            "displayText": "12.42",
            "rawValueJson": "12.42",
            "numberFormat": "General"
          },
          {
            "row": 3,
            "column": 10,
            "displayText": "9.9",
            "rawValueJson": "9.9",
            "numberFormat": "General"
          },
          {
            "row": 3,
            "column": 11,
            "displayText": "Asia",
            "rawValueJson": "\"Asia\"",
            "numberFormat": "General"
          },
          {
            "row": 4,
            "column": 1,
            "displayText": "Russia",
            "rawValueJson": "\"Russia\"",
            "numberFormat": "General"
          },
          {
            "row": 4,
            "column": 2,
            "displayText": "2004",
            "rawValueJson": "2004",
            "numberFormat": "General"
          },
          {
            "row": 4,
            "column": 3,
            "displayText": "6991.3",
            "rawValueJson": "6991.3",
            "numberFormat": "General"
          },
          {
            "row": 4,
            "column": 4,
            "displayText": "3972.36",
            "rawValueJson": "3972.36",
            "numberFormat": "General"
          },
          {
            "row": 4,
            "column": 5,
            "displayText": "40.85",
            "rawValueJson": "40.85",
            "numberFormat": "General"
          },
          {
            "row": 4,
            "column": 6,
            "displayText": "22.94",
            "rawValueJson": "22.94",
            "numberFormat": "General"
          },
          {
            "row": 4,
            "column": 7,
            "displayText": "15.48",
            "rawValueJson": "15.48",
            "numberFormat": "General"
          },
          {
            "row": 4,
            "column": 8,
            "displayText": "15.28",
            "rawValueJson": "15.28",
            "numberFormat": "General"
          },
          {
            "row": 4,
            "column": 9,
            "displayText": "7.1",
            "rawValueJson": "7.1",
            "numberFormat": "General"
          },
          {
            "row": 4,
            "column": 10,
            "displayText": "9.59",
            "rawValueJson": "9.59",
            "numberFormat": "General"
          },
          {
            "row": 4,
            "column": 11,
            "displayText": "Europe",
            "rawValueJson": "\"Europe\"",
            "numberFormat": "General"
          },
          {
            "row": 5,
            "column": 1,
            "displayText": "South Africa",
            "rawValueJson": "\"South Africa\"",
            "numberFormat": "General"
          },
          {
            "row": 5,
            "column": 2,
            "displayText": "2011",
            "rawValueJson": "2011",
            "numberFormat": "General"
          },
          {
            "row": 5,
            "column": 3,
            "displayText": "6628.04",
            "rawValueJson": "6628.04",
            "numberFormat": "General"
          },
          {
            "row": 5,
            "column": 4,
            "displayText": "6755.75",
            "rawValueJson": "6755.75",
            "numberFormat": "General"
          },
          {
            "row": 5,
            "column": 5,
            "displayText": "30.38",
            "rawValueJson": "30.38",
            "numberFormat": "General"
          },
          {
            "row": 5,
            "column": 6,
            "displayText": "15.69",
            "rawValueJson": "15.69",
            "numberFormat": "General"
          },
          {
            "row": 5,
            "column": 7,
            "displayText": "8.03",
            "rawValueJson": "8.03",
            "numberFormat": "General"
          },
          {
            "row": 5,
            "column": 8,
            "displayText": "6.66",
            "rawValueJson": "6.66",
            "numberFormat": "General"
          },
          {
            "row": 5,
            "column": 9,
            "displayText": "11.76",
            "rawValueJson": "11.76",
            "numberFormat": "General"
          },
          {
            "row": 5,
            "column": 10,
            "displayText": "11.04",
            "rawValueJson": "11.04",
            "numberFormat": "General"
          },
          {
            "row": 5,
            "column": 11,
            "displayText": "Africa",
            "rawValueJson": "\"Africa\"",
            "numberFormat": "General"
          },
          {
            "row": 6,
            "column": 1,
            "displayText": "Brazil",
            "rawValueJson": "\"Brazil\"",
            "numberFormat": "General"
          },
          {
            "row": 6,
            "column": 2,
            "displayText": "2015",
            "rawValueJson": "2015",
            "numberFormat": "General"
          },
          {
            "row": 6,
            "column": 3,
            "displayText": "2434.27",
            "rawValueJson": "2434.27",
            "numberFormat": "General"
          },
          {
            "row": 6,
            "column": 4,
            "displayText": "2656.36",
            "rawValueJson": "2656.36",
            "numberFormat": "General"
          },
          {
            "row": 6,
            "column": 5,
            "displayText": "49.27",
            "rawValueJson": "49.27",
            "numberFormat": "General"
          },
          {
            "row": 6,
            "column": 6,
            "displayText": "12.44",
            "rawValueJson": "12.44",
            "numberFormat": "General"
          },
          {
            "row": 6,
            "column": 7,
            "displayText": "25.06",
            "rawValueJson": "25.06",
            "numberFormat": "General"
          },
          {
            "row": 6,
            "column": 8,
            "displayText": "9.34",
            "rawValueJson": "9.34",
            "numberFormat": "General"
          },
          {
            "row": 6,
            "column": 9,
            "displayText": "3.63",
            "rawValueJson": "3.63",
            "numberFormat": "General"
          },
          {
            "row": 6,
            "column": 10,
            "displayText": "15.09",
            "rawValueJson": "15.09",
            "numberFormat": "General"
          },
          {
            "row": 6,
            "column": 11,
            "displayText": "South America",
            "rawValueJson": "\"South America\"",
            "numberFormat": "General"
          }
        ]
      }
    ],
    "tableName": "Table_d3b27d7e",
    "hasMergedcells": false,
    "boundaryConfidence": 1,
    "sheetName": "Data",
    "isDataSampled": true,
    "primaryTable": {
      "tableType": "columnMajorFlat",
      "hasTotalRow": false,
      "hasTotalColumn": false,
      "sampleCells": [
        {
          "row": 1,
          "column": 1,
          "displayText": "Country",
          "rawValueJson": "\"Country\"",
          "numberFormat": "General"
        },
        {
          "row": 1,
          "column": 2,
          "displayText": "Year",
          "rawValueJson": "\"Year\"",
          "numberFormat": "General"
        },
        {
          "row": 1,
          "column": 3,
          "displayText": "Average_Monthly_Income",
          "rawValueJson": "\"Average_Monthly_Income\"",
          "numberFormat": "General"
        },
        {
          "row": 1,
          "column": 4,
          "displayText": "Cost_of_Living",
          "rawValueJson": "\"Cost_of_Living\"",
          "numberFormat": "General"
        },
        {
          "row": 1,
          "column": 5,
          "displayText": "Housing_Cost_Percentage",
          "rawValueJson": "\"Housing_Cost_Percentage\"",
          "numberFormat": "General"
        },
        {
          "row": 1,
          "column": 6,
          "displayText": "Tax_Rate",
          "rawValueJson": "\"Tax_Rate\"",
          "numberFormat": "General"
        },
        {
          "row": 1,
          "column": 7,
          "displayText": "Savings_Percentage",
          "rawValueJson": "\"Savings_Percentage\"",
          "numberFormat": "General"
        },
        {
          "row": 1,
          "column": 8,
          "displayText": "Healthcare_Cost_Percentage",
          "rawValueJson": "\"Healthcare_Cost_Percentage\"",
          "numberFormat": "General"
        },
        {
          "row": 1,
          "column": 9,
          "displayText": "Education_Cost_Percentage",
          "rawValueJson": "\"Education_Cost_Percentage\"",
          "numberFormat": "General"
        },
        {
          "row": 1,
          "column": 10,
          "displayText": "Transportation_Cost_Percentage",
          "rawValueJson": "\"Transportation_Cost_Percentage\"",
          "numberFormat": "General"
        },
        {
          "row": 1,
          "column": 11,
          "displayText": "Region",
          "rawValueJson": "\"Region\"",
          "numberFormat": "General"
        },
        {
          "row": 2,
          "column": 1,
          "displayText": "Australia",
          "rawValueJson": "\"Australia\"",
          "numberFormat": "General"
        },
        {
          "row": 2,
          "column": 2,
          "displayText": "2013",
          "rawValueJson": "2013",
          "numberFormat": "General"
        },
        {
          "row": 2,
          "column": 3,
          "displayText": "3483.92",
          "rawValueJson": "3483.92",
          "numberFormat": "General"
        },
        {
          "row": 2,
          "column": 4,
          "displayText": "1106.07",
          "rawValueJson": "1106.07",
          "numberFormat": "General"
        },
        {
          "row": 2,
          "column": 5,
          "displayText": "32.09",
          "rawValueJson": "32.09",
          "numberFormat": "General"
        },
        {
          "row": 2,
          "column": 6,
          "displayText": "27.5",
          "rawValueJson": "27.5",
          "numberFormat": "General"
        },
        {
          "row": 2,
          "column": 7,
          "displayText": "1.74",
          "rawValueJson": "1.74",
          "numberFormat": "General"
        },
        {
          "row": 2,
          "column": 8,
          "displayText": "18.23",
          "rawValueJson": "18.23",
          "numberFormat": "General"
        },
        {
          "row": 2,
          "column": 9,
          "displayText": "6.94",
          "rawValueJson": "6.94",
          "numberFormat": "General"
        },
        {
          "row": 2,
          "column": 10,
          "displayText": "17.19",
          "rawValueJson": "17.19",
          "numberFormat": "General"
        },
        {
          "row": 2,
          "column": 11,
          "displayText": "Oceania",
          "rawValueJson": "\"Oceania\"",
          "numberFormat": "General"
        },
        {
          "row": 3,
          "column": 1,
          "displayText": "India",
          "rawValueJson": "\"India\"",
          "numberFormat": "General"
        },
        {
          "row": 3,
          "column": 2,
          "displayText": "2019",
          "rawValueJson": "2019",
          "numberFormat": "General"
        },
        {
          "row": 3,
          "column": 3,
          "displayText": "7771.03",
          "rawValueJson": "7771.03",
          "numberFormat": "General"
        },
        {
          "row": 3,
          "column": 4,
          "displayText": "5422.78",
          "rawValueJson": "5422.78",
          "numberFormat": "General"
        },
        {
          "row": 3,
          "column": 5,
          "displayText": "25.21",
          "rawValueJson": "25.21",
          "numberFormat": "General"
        },
        {
          "row": 3,
          "column": 6,
          "displayText": "29.3",
          "rawValueJson": "29.3",
          "numberFormat": "General"
        },
        {
          "row": 3,
          "column": 7,
          "displayText": "3.35",
          "rawValueJson": "3.35",
          "numberFormat": "General"
        },
        {
          "row": 3,
          "column": 8,
          "displayText": "17.21",
          "rawValueJson": "17.21",
          "numberFormat": "General"
        },
        {
          "row": 3,
          "column": 9,
          "displayText": "12.42",
          "rawValueJson": "12.42",
          "numberFormat": "General"
        },
        {
          "row": 3,
          "column": 10,
          "displayText": "9.9",
          "rawValueJson": "9.9",
          "numberFormat": "General"
        },
        {
          "row": 3,
          "column": 11,
          "displayText": "Asia",
          "rawValueJson": "\"Asia\"",
          "numberFormat": "General"
        },
        {
          "row": 4,
          "column": 1,
          "displayText": "Russia",
          "rawValueJson": "\"Russia\"",
          "numberFormat": "General"
        },
        {
          "row": 4,
          "column": 2,
          "displayText": "2004",
          "rawValueJson": "2004",
          "numberFormat": "General"
        },
        {
          "row": 4,
          "column": 3,
          "displayText": "6991.3",
          "rawValueJson": "6991.3",
          "numberFormat": "General"
        },
        {
          "row": 4,
          "column": 4,
          "displayText": "3972.36",
          "rawValueJson": "3972.36",
          "numberFormat": "General"
        },
        {
          "row": 4,
          "column": 5,
          "displayText": "40.85",
          "rawValueJson": "40.85",
          "numberFormat": "General"
        },
        {
          "row": 4,
          "column": 6,
          "displayText": "22.94",
          "rawValueJson": "22.94",
          "numberFormat": "General"
        },
        {
          "row": 4,
          "column": 7,
          "displayText": "15.48",
          "rawValueJson": "15.48",
          "numberFormat": "General"
        },
        {
          "row": 4,
          "column": 8,
          "displayText": "15.28",
          "rawValueJson": "15.28",
          "numberFormat": "General"
        },
        {
          "row": 4,
          "column": 9,
          "displayText": "7.1",
          "rawValueJson": "7.1",
          "numberFormat": "General"
        },
        {
          "row": 4,
          "column": 10,
          "displayText": "9.59",
          "rawValueJson": "9.59",
          "numberFormat": "General"
        },
        {
          "row": 4,
          "column": 11,
          "displayText": "Europe",
          "rawValueJson": "\"Europe\"",
          "numberFormat": "General"
        },
        {
          "row": 5,
          "column": 1,
          "displayText": "South Africa",
          "rawValueJson": "\"South Africa\"",
          "numberFormat": "General"
        },
        {
          "row": 5,
          "column": 2,
          "displayText": "2011",
          "rawValueJson": "2011",
          "numberFormat": "General"
        },
        {
          "row": 5,
          "column": 3,
          "displayText": "6628.04",
          "rawValueJson": "6628.04",
          "numberFormat": "General"
        },
        {
          "row": 5,
          "column": 4,
          "displayText": "6755.75",
          "rawValueJson": "6755.75",
          "numberFormat": "General"
        },
        {
          "row": 5,
          "column": 5,
          "displayText": "30.38",
          "rawValueJson": "30.38",
          "numberFormat": "General"
        },
        {
          "row": 5,
          "column": 6,
          "displayText": "15.69",
          "rawValueJson": "15.69",
          "numberFormat": "General"
        },
        {
          "row": 5,
          "column": 7,
          "displayText": "8.03",
          "rawValueJson": "8.03",
          "numberFormat": "General"
        },
        {
          "row": 5,
          "column": 8,
          "displayText": "6.66",
          "rawValueJson": "6.66",
          "numberFormat": "General"
        },
        {
          "row": 5,
          "column": 9,
          "displayText": "11.76",
          "rawValueJson": "11.76",
          "numberFormat": "General"
        },
        {
          "row": 5,
          "column": 10,
          "displayText": "11.04",
          "rawValueJson": "11.04",
          "numberFormat": "General"
        },
        {
          "row": 5,
          "column": 11,
          "displayText": "Africa",
          "rawValueJson": "\"Africa\"",
          "numberFormat": "General"
        },
        {
          "row": 6,
          "column": 1,
          "displayText": "Brazil",
          "rawValueJson": "\"Brazil\"",
          "numberFormat": "General"
        },
        {
          "row": 6,
          "column": 2,
          "displayText": "2015",
          "rawValueJson": "2015",
          "numberFormat": "General"
        },
        {
          "row": 6,
          "column": 3,
          "displayText": "2434.27",
          "rawValueJson": "2434.27",
          "numberFormat": "General"
        },
        {
          "row": 6,
          "column": 4,
          "displayText": "2656.36",
          "rawValueJson": "2656.36",
          "numberFormat": "General"
        },
        {
          "row": 6,
          "column": 5,
          "displayText": "49.27",
          "rawValueJson": "49.27",
          "numberFormat": "General"
        },
        {
          "row": 6,
          "column": 6,
          "displayText": "12.44",
          "rawValueJson": "12.44",
          "numberFormat": "General"
        },
        {
          "row": 6,
          "column": 7,
          "displayText": "25.06",
          "rawValueJson": "25.06",
          "numberFormat": "General"
        },
        {
          "row": 6,
          "column": 8,
          "displayText": "9.34",
          "rawValueJson": "9.34",
          "numberFormat": "General"
        },
        {
          "row": 6,
          "column": 9,
          "displayText": "3.63",
          "rawValueJson": "3.63",
          "numberFormat": "General"
        },
        {
          "row": 6,
          "column": 10,
          "displayText": "15.09",
          "rawValueJson": "15.09",
          "numberFormat": "General"
        },
        {
          "row": 6,
          "column": 11,
          "displayText": "South America",
          "rawValueJson": "\"South America\"",
          "numberFormat": "General"
        }
      ]
    },
    "sampledLines": [
      1,
      2,
      3,
      4,
      5,
      6,
      7,
      8,
      9,
      10,
      11,
      12,
      13,
      14,
      15,
      16,
      17,
      18,
      19,
      20,
      21,
      22,
      23,
      24,
      25,
      26,
      27,
      28,
      29,
      30,
      31,
      32,
      33,
      34,
      35,
      36,
      37,
      38,
      39,
      40,
      41,
      42,
      43,
      44,
      45,
      46,
      47,
      48,
      49,
      50,
      51,
      52,
      53,
      54,
      55,
      56,
      57,
      58,
      59,
      60,
      61,
      62,
      63,
      64,
      65,
      66,
      67,
      68,
      69,
      70,
      71,
      72,
      73,
      74,
      75,
      76,
      77,
      78,
      79,
      80,
      81,
      82,
      83,
      84,
      85,
      86,
      87,
      88,
      89,
      90,
      91,
      92,
      93,
      94,
      95,
      96,
      97,
      98,
      99,
      100,
      101,
      102,
      103,
      104,
      105,
      106,
      107,
      108,
      109,
      110,
      111,
      112,
      113,
      114,
      115,
      116,
      117,
      118,
      119,
      120,
      121,
      122,
      123,
      124,
      125,
      126,
      127,
      128,
      129,
      130,
      131,
      132,
      133,
      134,
      135,
      136,
      137,
      138,
      139,
      140,
      141,
      142,
      143,
      144,
      145,
      146,
      147,
      148,
      149,
      150,
      151,
      152,
      153,
      154,
      155,
      156,
      157,
      158,
      159,
      160,
      161,
      162,
      163,
      164,
      165,
      166,
      167,
      168,
      169,
      170,
      171,
      172,
      173,
      174,
      175,
      176,
      177,
      178,
      179,
      180,
      181,
      182,
      183,
      184,
      185,
      186,
      187,
      188,
      189,
      190,
      191,
      192,
      193,
      194,
      195,
      196,
      197,
      198,
      199,
      200,
      201,
      202,
      203,
      204,
      205,
      206,
      207,
      208,
      209,
      210,
      211,
      212,
      213,
      214,
      215,
      216,
      217,
      218,
      219,
      220,
      221,
      222,
      223,
      224,
      225,
      226,
      227,
      228,
      229,
      230,
      231,
      232,
      233,
      234,
      235,
      236,
      237,
      238,
      239,
      240,
      241,
      242,
      243,
      244,
      245,
      246,
      247,
      248,
      249,
      250,
      501,
      500,
      499,
      498,
      497,
      496,
      495,
      494,
      493,
      492,
      491,
      490,
      489,
      488,
      487,
      486,
      485,
      484,
      483,
      482,
      481,
      480,
      479,
      478,
      477,
      476,
      475,
      474,
      473,
      472,
      471,
      470,
      469,
      468,
      467,
      466,
      465,
      464,
      463,
      462,
      461,
      460,
      459,
      458,
      457,
      456,
      455,
      454,
      453,
      452,
      451,
      450,
      449,
      448,
      447,
      446,
      445,
      444,
      443,
      442,
      441,
      440,
      439,
      438,
      437,
      436,
      435,
      434,
      433,
      432,
      431,
      430,
      429,
      428,
      427,
      426,
      425,
      424,
      423,
      422,
      421,
      420,
      419,
      418,
      417,
      416,
      415,
      414,
      413,
      412,
      411,
      410,
      409,
      408,
      407,
      406,
      405,
      404,
      403,
      402,
      401,
      400,
      399,
      398,
      397,
      396,
      395,
      394,
      393,
      392,
      391,
      390,
      389,
      388,
      387,
      386,
      385,
      384,
      383,
      382,
      381,
      380,
      379,
      378,
      377,
      376,
      375,
      374,
      373,
      372,
      371,
      370,
      369,
      368,
      367,
      366,
      365,
      364,
      363,
      362,
      361,
      360,
      359,
      358,
      357,
      356,
      355,
      354,
      353,
      352,
      351,
      350,
      349,
      348,
      347,
      346,
      345,
      344,
      343,
      342,
      341,
      340,
      339,
      338,
      337,
      336,
      335,
      334,
      333,
      332,
      331,
      330,
      329,
      328,
      327,
      326,
      325,
      324,
      323,
      322,
      321,
      320,
      319,
      318,
      317,
      316,
      315,
      314,
      313,
      312,
      311,
      310,
      309,
      308,
      307,
      306,
      305,
      304,
      303,
      302,
      301,
      300,
      299,
      298,
      297,
      296,
      295,
      294,
      293,
      292,
      291,
      290,
      289,
      288,
      287,
      286,
      285,
      284,
      283,
      282,
      281,
      280,
      279,
      278,
      277,
      276,
      275,
      274,
      273,
      272,
      271,
      270,
      269,
      268,
      267,
      266,
      265,
      264,
      263,
      262,
      261,
      260,
      259,
      258,
      257,
      256,
      255,
      254,
      253,
      252
    ],
    "samplingScheme": 1,
    "H_": {
      "T_": "AugLoop_ExcelTableAi_ExcelRecognizedTableNew",
      "B_": [
        "AugLoop_Excel_ExcelRangeWrapperAnnotation",
        "AugLoop_Core_Annotation"
      ]
    },
    "id": "4671f619-4235-4475-a706-2d9b06218c79",
    "ownerId": "ExcelTableRecognitionReducer",
    "M_": {
      "state": 20
    }
  }
]