[
  {
    "range": {
      "worksheetId": "{388D9BE7-03EA-42EB-9706-77C71DDF198C}",
      "top": 1,
      "left": 1,
      "bottom": 27,
      "right": 19
    },
    "interpretations": [
      {
        "confidence": 1,
        "location": {
          "worksheetId": "{388D9BE7-03EA-42EB-9706-77C71DDF198C}",
          "top": 1,
          "bottom": 27,
          "left": 1,
          "right": 19
        },
        "orientation": "columnMajor",
        "headerRowCount": 1,
        "headerColumnCount": 0,
        "fields": [
          {
            "classification": "dimension",
            "aggregations": [],
            "headerReferences": [],
            "isTextual": false
          },
          {
            "classification": "dimension",
            "aggregations": [],
            "headerReferences": [],
            "isTextual": false
          },
          {
            "classification": "dimension",
            "aggregations": [],
            "headerReferences": [],
            "isTextual": false
          },
          {
            "classification": "dimension",
            "aggregations": [],
            "headerReferences": [],
            "isTextual": false
          },
          {
            "classification": "dimension",
            "aggregations": [],
            "headerReferences": [],
            "isTextual": false
          },
          {
            "classification": "dimension",
            "aggregations": [],
            "headerReferences": [],
            "isTextual": false
          },
          {
            "classification": "dimension",
            "aggregations": [],
            "headerReferences": [],
            "isTextual": false
          },
          {
            "classification": "dimension",
            "aggregations": [],
            "headerReferences": [],
            "isTextual": false
          },
          {
            "classification": "dimension",
            "aggregations": [],
            "headerReferences": [],
            "isTextual": false
          },
          {
            "classification": "dimension",
            "aggregations": [],
            "headerReferences": [],
            "isTextual": false
          },
          {
            "classification": "dimension",
            "aggregations": [],
            "headerReferences": [],
            "isTextual": false
          },
          {
            "classification": "dimension",
            "aggregations": [],
            "headerReferences": [],
            "isTextual": false
          },
          {
            "classification": "dimension",
            "aggregations": [],
            "headerReferences": [],
            "isTextual": false
          },
          {
            "classification": "dimension",
            "aggregations": [],
            "headerReferences": [],
            "isTextual": true
          },
          {
            "classification": "dimension",
            "aggregations": [],
            "headerReferences": [],
            "isTextual": true
          },
          {
            "classification": "dimension",
            "aggregations": [],
            "headerReferences": [],
            "isTextual": true
          },
          {
            "classification": "dimension",
            "aggregations": [],
            "headerReferences": [],
            "isTextual": false
          },
          {
            "classification": "dimension",
            "aggregations": [],
            "headerReferences": [],
            "isTextual": false
          },
          {
            "classification": "dimension",
            "aggregations": [],
            "headerReferences": [],
            "isTextual": true
          }
        ],
        "headerNames": [
          "\"Timestamp\"",
          "\"Email Address\"",
          "\"Discord Username\"",
          "\"Minecraft Username\"",
          "\"Preferred Name\"",
          "\"Pronouns\"",
          "\"Age\"",
          "\"Link to YouTube Channel\"",
          "\"Links to Other Platforms\"",
          "\"Have you joined our Discord? (https://discord.gg/B4Set59eKb)\"",
          "\"Have you ever played on an SMP server?\"",
          "\"Have you ever created a Minecraft let's play series?\"",
          "\"Link us one video of yours that you are most proud of. Why is it your favorite?\"",
          "\"What kind of playstyle would you bring to AutoCraft SMP?\"",
          "\"What kind of builds would you add to AutoCraft SMP?\"",
          "\"What kind of content would you create on AutoCraft SMP?\"",
          "\"There is always something happening on the server!\\nWhat are you interested in being a part of?\"",
          "\"Build Screenshots\"",
          "\"Is there anything else you would like to add to your AutoCraft SMP application?\""
        ],
        "sampleCellData": [
          {
            "row": 1,
            "column": 1,
            "displayText": "Timestamp",
            "rawValueJson": "\"Timestamp\"",
            "numberFormat": "General"
          },
          {
            "row": 1,
            "column": 2,
            "displayText": "Email Address",
            "rawValueJson": "\"Email Address\"",
            "numberFormat": "General"
          },
          {
            "row": 1,
            "column": 3,
            "displayText": "Discord Username",
            "rawValueJson": "\"Discord Username\"",
            "numberFormat": "General"
          },
          {
            "row": 1,
            "column": 4,
            "displayText": "Minecraft Username",
            "rawValueJson": "\"Minecraft Username\"",
            "numberFormat": "General"
          },
          {
            "row": 1,
            "column": 5,
            "displayText": "Preferred Name",
            "rawValueJson": "\"Preferred Name\"",
            "numberFormat": "General"
          },
          {
            "row": 1,
            "column": 6,
            "displayText": "Pronouns",
            "rawValueJson": "\"Pronouns\"",
            "numberFormat": "General"
          },
          {
            "row": 1,
            "column": 7,
            "displayText": "Age",
            "rawValueJson": "\"Age\"",
            "numberFormat": "General"
          },
          {
            "row": 1,
            "column": 8,
            "displayText": "Link to YouTube Channel",
            "rawValueJson": "\"Link to YouTube Channel\"",
            "numberFormat": "General"
          },
          {
            "row": 1,
            "column": 9,
            "displayText": "Links to Other Platforms",
            "rawValueJson": "\"Links to Other Platforms\"",
            "numberFormat": "General"
          },
          {
            "row": 1,
            "column": 10,
            "displayText": "Have you joined our Discord? (https://discord.gg/B4Set59eKb)",
            "rawValueJson": "\"Have you joined our Discord? (https://discord.gg/B4Set59eKb)\"",
            "numberFormat": "General"
          },
          {
            "row": 1,
            "column": 11,
            "displayText": "Have you ever played on an SMP server?",
            "rawValueJson": "\"Have you ever played on an SMP server?\"",
            "numberFormat": "General"
          },
          {
            "row": 1,
            "column": 12,
            "displayText": "Have you ever created a Minecraft let's play series?",
            "rawValueJson": "\"Have you ever created a Minecraft let's play series?\"",
            "numberFormat": "General"
          },
          {
            "row": 1,
            "column": 13,
            "displayText": "Link us one video of yours that you are most proud of. Why is it your favorite?",
            "rawValueJson": "\"Link us one video of yours that you are most proud of. Why is it your favorite?\"",
            "numberFormat": "General"
          },
          {
            "row": 1,
            "column": 14,
            "displayText": "What kind of playstyle would you bring to AutoCraft SMP?",
            "rawValueJson": "\"What kind of playstyle would you bring to AutoCraft SMP?\"",
            "numberFormat": "General"
          },
          {
            "row": 1,
            "column": 15,
            "displayText": "What kind of builds would you add to AutoCraft SMP?",
            "rawValueJson": "\"What kind of builds would you add to AutoCraft SMP?\"",
            "numberFormat": "General"
          },
          {
            "row": 1,
            "column": 16,
            "displayText": "What kind of content would you create on AutoCraft SMP?",
            "rawValueJson": "\"What kind of content would you create on AutoCraft SMP?\"",
            "numberFormat": "General"
          },
          {
            "row": 1,
            "column": 17,
            "displayText": "There is always something happening on the server!\nWhat are you interested in being a part of?",
            "rawValueJson": "\"There is always something happening on the server!\\nWhat are you interested in being a part of?\"",
            "numberFormat": "General"
          },
          {
            "row": 1,
            "column": 18,
            "displayText": "Build Screenshots",
            "rawValueJson": "\"Build Screenshots\"",
            "numberFormat": "General"
          },
          {
            "row": 1,
            "column": 19,
            "displayText": "Is there anything else you would like to add to your AutoCraft SMP application?",
            "rawValueJson": "\"Is there anything else you would like to add to your AutoCraft SMP application?\"",
            "numberFormat": "General"
          },
          {
            "row": 2,
            "column": 1,
            "displayText": "5/16/2024 7:28:38",
            "rawValueJson": "45428.3115527662",
            "numberFormat": "m/d/yyyy h:mm:ss"
          },
          {
            "row": 2,
            "column": 6,
            "displayText": "He/Him/His",
            "rawValueJson": "\"He/Him/His\"",
            "numberFormat": "General"
          },
          {
            "row": 2,
            "column": 7,
            "displayText": "25",
            "rawValueJson": "25",
            "numberFormat": "General"
          },
          {
            "row": 2,
            "column": 10,
            "displayText": "Yes",
            "rawValueJson": "\"Yes\"",
            "numberFormat": "General"
          },
          {
            "row": 2,
            "column": 11,
            "displayText": "Yes",
            "rawValueJson": "\"Yes\"",
            "numberFormat": "General"
          },
          {
            "row": 2,
            "column": 12,
            "displayText": "Yes",
            "rawValueJson": "\"Yes\"",
            "numberFormat": "General"
          },
          {
            "row": 2,
            "column": 14,
            "displayText": "Definitely a builder. But I love an adventure!",
            "rawValueJson": "\"Definitely a builder. But I love an adventure!\"",
            "numberFormat": "General"
          },
          {
            "row": 2,
            "column": 15,
            "displayText": "Oh I got this awesome abandoned themepark/fair idea that has been in my head and creative world that I would absolutely love to make a reality!",
            "rawValueJson": "\"Oh I got this awesome abandoned themepark/fair idea that has been in my head and creative world that I would absolutely love to make a reality!\"",
            "numberFormat": "General"
          },
          {
            "row": 2,
            "column": 16,
            "displayText": "Definitely building focussed, but I am also big on collaboration and adventures. Meeting new people and making new memories.",
            "rawValueJson": "\"Definitely building focussed, but I am also big on collaboration and adventures. Meeting new people and making new memories.\"",
            "numberFormat": "General"
          },
          {
            "row": 2,
            "column": 17,
            "displayText": "Build Collaborations, Storyline Collaborations, Stream Days, Discord Events, Server Meetings",
            "rawValueJson": "\"Build Collaborations, Storyline Collaborations, Stream Days, Discord Events, Server Meetings\"",
            "numberFormat": "General"
          },
          {
            "row": 2,
            "column": 19,
            "displayText": "Not really I hope I can join you all in the amazing new memories of Season 5 of Autocraft",
            "rawValueJson": "\"Not really I hope I can join you all in the amazing new memories of Season 5 of Autocraft\"",
            "numberFormat": "General"
          },
          {
            "row": 3,
            "column": 1,
            "displayText": "5/16/2024 10:40:01",
            "rawValueJson": "45428.44445930555",
            "numberFormat": "m/d/yyyy h:mm:ss"
          },
          {
            "row": 3,
            "column": 6,
            "displayText": "He/Him/His",
            "rawValueJson": "\"He/Him/His\"",
            "numberFormat": "General"
          },
          {
            "row": 3,
            "column": 7,
            "displayText": "I would like to keep that private plz",
            "rawValueJson": "\"I would like to keep that private plz\"",
            "numberFormat": "General"
          },
          {
            "row": 3,
            "column": 10,
            "displayText": "Yes",
            "rawValueJson": "\"Yes\"",
            "numberFormat": "General"
          },
          {
            "row": 3,
            "column": 11,
            "displayText": "Yes",
            "rawValueJson": "\"Yes\"",
            "numberFormat": "General"
          },
          {
            "row": 3,
            "column": 12,
            "displayText": "No",
            "rawValueJson": "\"No\"",
            "numberFormat": "General"
          },
          {
            "row": 3,
            "column": 14,
            "displayText": "I would consider myself a builder and I'm not sure if this is what you are asking but im also just someone who likes to have have fun messing around.",
            "rawValueJson": "\"I would consider myself a builder and I'm not sure if this is what you are asking but im also just someone who likes to have have fun messing around.\"",
            "numberFormat": "General"
          },
          {
            "row": 3,
            "column": 15,
            "displayText": "I was thinking if I joined Auto Crafters I would maybe build a Big Mushroom Village Bigger than anything I've ever built before",
            "rawValueJson": "\"I was thinking if I joined Auto Crafters I would maybe build a Big Mushroom Village Bigger than anything I've ever built before\"",
            "numberFormat": "General"
          },
          {
            "row": 3,
            "column": 16,
            "displayText": "If I join Auto Crafters, I plan to still make Kingcraft content. And as for videos I would release on the auto crafters It would probably be Getting to know you guys working on my base And Shenanigans\\interactions",
            "rawValueJson": "\"If I join Auto Crafters, I plan to still make Kingcraft content. And as for videos I would release on the auto crafters It would probably be Getting to know you guys working on my base And Shenanigans\\\\interactions\"",
            "numberFormat": "General"
          },
          {
            "row": 3,
            "column": 17,
            "displayText": "Build Collaborations, Storyline Collaborations, Server Meetings",
            "rawValueJson": "\"Build Collaborations, Storyline Collaborations, Server Meetings\"",
            "numberFormat": "General"
          },
          {
            "row": 4,
            "column": 1,
            "displayText": "5/16/2024 17:58:49",
            "rawValueJson": "45428.74918337963",
            "numberFormat": "m/d/yyyy h:mm:ss"
          },
          {
            "row": 4,
            "column": 6,
            "displayText": "She/Her/Hers",
            "rawValueJson": "\"She/Her/Hers\"",
            "numberFormat": "General"
          },
          {
            "row": 4,
            "column": 7,
            "displayText": "21",
            "rawValueJson": "21",
            "numberFormat": "General"
          },
          {
            "row": 4,
            "column": 10,
            "displayText": "Yes",
            "rawValueJson": "\"Yes\"",
            "numberFormat": "General"
          },
          {
            "row": 4,
            "column": 11,
            "displayText": "Yes",
            "rawValueJson": "\"Yes\"",
            "numberFormat": "General"
          },
          {
            "row": 4,
            "column": 12,
            "displayText": "No",
            "rawValueJson": "\"No\"",
            "numberFormat": "General"
          },
          {
            "row": 4,
            "column": 14,
            "displayText": "Builder ",
            "rawValueJson": "\"Builder \"",
            "numberFormat": "General"
          },
          {
            "row": 4,
            "column": 15,
            "displayText": "Huge buildings I can try for my base and shops ",
            "rawValueJson": "\"Huge buildings I can try for my base and shops \"",
            "numberFormat": "General"
          },
          {
            "row": 4,
            "column": 16,
            "displayText": "I don’t know ",
            "rawValueJson": "\"I don’t know \"",
            "numberFormat": "General"
          },
          {
            "row": 4,
            "column": 17,
            "displayText": "Build Collaborations, Stream Days, Discord Events, Server Meetings",
            "rawValueJson": "\"Build Collaborations, Stream Days, Discord Events, Server Meetings\"",
            "numberFormat": "General"
          },
          {
            "row": 4,
            "column": 19,
            "displayText": "👆🏻 up to the Build Screenshots that’s is an old build from me and my dad build from another server ",
            "rawValueJson": "\"👆🏻 up to the Build Screenshots that’s is an old build from me and my dad build from another server \"",
            "numberFormat": "General"
          },
          {
            "row": 5,
            "column": 1,
            "displayText": "5/16/2024 19:08:01",
            "rawValueJson": "45428.79723232639",
            "numberFormat": "m/d/yyyy h:mm:ss"
          },
          {
            "row": 5,
            "column": 6,
            "displayText": "He/Him/His, They/Them/Theirs",
            "rawValueJson": "\"He/Him/His, They/Them/Theirs\"",
            "numberFormat": "General"
          },
          {
            "row": 5,
            "column": 7,
            "displayText": "35",
            "rawValueJson": "35",
            "numberFormat": "General"
          },
          {
            "row": 5,
            "column": 10,
            "displayText": "Yes",
            "rawValueJson": "\"Yes\"",
            "numberFormat": "General"
          },
          {
            "row": 5,
            "column": 11,
            "displayText": "Yes",
            "rawValueJson": "\"Yes\"",
            "numberFormat": "General"
          },
          {
            "row": 5,
            "column": 12,
            "displayText": "Yes",
            "rawValueJson": "\"Yes\"",
            "numberFormat": "General"
          },
          {
            "row": 5,
            "column": 14,
            "displayText": "Builder mainly but a bit of an explorer sometimes",
            "rawValueJson": "\"Builder mainly but a bit of an explorer sometimes\"",
            "numberFormat": "General"
          },
          {
            "row": 5,
            "column": 15,
            "displayText": "Base - Thinking of a few ideas maybe a fantasy/medivel or a whimsical build. Though there is a water base I've been wanting to do for a while\nShop - Maybe a stone shop or my personal favorite amethyst shop would be fun",
            "rawValueJson": "\"Base - Thinking of a few ideas maybe a fantasy/medivel or a whimsical build. Though there is a water base I've been wanting to do for a while\\nShop - Maybe a stone shop or my personal favorite amethyst shop would be fun\"",
            "numberFormat": "General"
          },
          {
            "row": 5,
            "column": 16,
            "displayText": "Weekly Let's play videos. Occasional shorts/tik toks, and weekly streams",
            "rawValueJson": "\"Weekly Let's play videos. Occasional shorts/tik toks, and weekly streams\"",
            "numberFormat": "General"
          },
          {
            "row": 5,
            "column": 17,
            "displayText": "Build Collaborations, Storyline Collaborations, Stream Days, Discord Events, Server Meetings",
            "rawValueJson": "\"Build Collaborations, Storyline Collaborations, Stream Days, Discord Events, Server Meetings\"",
            "numberFormat": "General"
          },
          {
            "row": 5,
            "column": 19,
            "displayText": "As stated before I've been a few SMPs before including - GrowthSMP, AzureSMP, PixieSMP and SovereignSMP. While I do have a set schedule for streams and my videos, I can be pretty flexible. I can be a bit on the reserved side at first but after you get to know me and especially if you get me on a topic I like, I may talk your ear off. I do like to try to change my skin for occasions whether the holidays or to fit my build or events as well. ",
            "rawValueJson": "\"As stated before I've been a few SMPs before including - GrowthSMP, AzureSMP, PixieSMP and SovereignSMP. While I do have a set schedule for streams and my videos, I can be pretty flexible. I can be a bit on the reserved side at first but after you get to know me and especially if you get me on a topic I like, I may talk your ear off. I do like to try to change my skin for occasions whether the holidays or to fit my build or events as well. \"",
            "numberFormat": "General"
          },
          {
            "row": 6,
            "column": 1,
            "displayText": "5/17/2024 10:20:44",
            "rawValueJson": "45429.43106231482",
            "numberFormat": "m/d/yyyy h:mm:ss"
          },
          {
            "row": 6,
            "column": 6,
            "displayText": "He/Him/His",
            "rawValueJson": "\"He/Him/His\"",
            "numberFormat": "General"
          },
          {
            "row": 6,
            "column": 7,
            "displayText": "21",
            "rawValueJson": "21",
            "numberFormat": "General"
          },
          {
            "row": 6,
            "column": 10,
            "displayText": "Yes",
            "rawValueJson": "\"Yes\"",
            "numberFormat": "General"
          },
          {
            "row": 6,
            "column": 11,
            "displayText": "Yes",
            "rawValueJson": "\"Yes\"",
            "numberFormat": "General"
          },
          {
            "row": 6,
            "column": 12,
            "displayText": "Yes",
            "rawValueJson": "\"Yes\"",
            "numberFormat": "General"
          },
          {
            "row": 6,
            "column": 14,
            "displayText": "I'm very much primarily into automatic farms, in some cases designing my own. Recently, though I have been getting more into building, working on more larger scale stuff.",
            "rawValueJson": "\"I'm very much primarily into automatic farms, in some cases designing my own. Recently, though I have been getting more into building, working on more larger scale stuff.\"",
            "numberFormat": "General"
          },
          {
            "row": 6,
            "column": 15,
            "displayText": "I'd like to revisit and expand on an old build of mine I called 'skylab'. It was essentially a big quartz disc over an ocean with some buildings. For 2.0 I'd probably add in more discs. perhaps built over a guardian farm. I have quite a geometric/futuristic build style so whatever I end up doing it's likely gonna feature lots of patterns and straight edges. As for shops, pretty much if I farm something I'll likely see if I can make a shop for it.  ",
            "rawValueJson": "\"I'd like to revisit and expand on an old build of mine I called 'skylab'. It was essentially a big quartz disc over an ocean with some buildings. For 2.0 I'd probably add in more discs. perhaps built over a guardian farm. I have quite a geometric/futuristic build style so whatever I end up doing it's likely gonna feature lots of patterns and straight edges. As for shops, pretty much if I farm something I'll likely see if I can make a shop for it.  \"",
            "numberFormat": "General"
          },
          {
            "row": 6,
            "column": 16,
            "displayText": "I's release just simple let's play videos every couple weeks or so. Similar to what I'm doing already with the Inter Realms SMP, alternating between servers for each video. I'm not much of a storyteller/lore person; I like to just show stuff as it is.",
            "rawValueJson": "\"I's release just simple let's play videos every couple weeks or so. Similar to what I'm doing already with the Inter Realms SMP, alternating between servers for each video. I'm not much of a storyteller/lore person; I like to just show stuff as it is.\"",
            "numberFormat": "General"
          },
          {
            "row": 6,
            "column": 17,
            "displayText": "Build Collaborations, Stream Days, Discord Events, Server Meetings",
            "rawValueJson": "\"Build Collaborations, Stream Days, Discord Events, Server Meetings\"",
            "numberFormat": "General"
          },
          {
            "row": 6,
            "column": 19,
            "displayText": "I've mentioned it above but I do also play on and make content from the Inter Realms SMP. I would be aiming to split my content evenly between the two servers but naturally there may be some sway one way or the other depending workload, events etc.",
            "rawValueJson": "\"I've mentioned it above but I do also play on and make content from the Inter Realms SMP. I would be aiming to split my content evenly between the two servers but naturally there may be some sway one way or the other depending workload, events etc.\"",
            "numberFormat": "General"
          }
        ]
      }
    ],
    "tableName": "Table1",
    "hasMergedcells": false,
    "boundaryConfidence": 1,
    "sheetName": "Form Responses 1",
    "isDataSampled": false,
    "primaryTable": {
      "tableType": "columnMajorFlat",
      "hasTotalRow": false,
      "hasTotalColumn": false,
      "sampleCells": [
        {
          "row": 1,
          "column": 1,
          "displayText": "Timestamp",
          "rawValueJson": "\"Timestamp\"",
          "numberFormat": "General"
        },
        {
          "row": 1,
          "column": 2,
          "displayText": "Email Address",
          "rawValueJson": "\"Email Address\"",
          "numberFormat": "General"
        },
        {
          "row": 1,
          "column": 3,
          "displayText": "Discord Username",
          "rawValueJson": "\"Discord Username\"",
          "numberFormat": "General"
        },
        {
          "row": 1,
          "column": 4,
          "displayText": "Minecraft Username",
          "rawValueJson": "\"Minecraft Username\"",
          "numberFormat": "General"
        },
        {
          "row": 1,
          "column": 5,
          "displayText": "Preferred Name",
          "rawValueJson": "\"Preferred Name\"",
          "numberFormat": "General"
        },
        {
          "row": 1,
          "column": 6,
          "displayText": "Pronouns",
          "rawValueJson": "\"Pronouns\"",
          "numberFormat": "General"
        },
        {
          "row": 1,
          "column": 7,
          "displayText": "Age",
          "rawValueJson": "\"Age\"",
          "numberFormat": "General"
        },
        {
          "row": 1,
          "column": 8,
          "displayText": "Link to YouTube Channel",
          "rawValueJson": "\"Link to YouTube Channel\"",
          "numberFormat": "General"
        },
        {
          "row": 1,
          "column": 9,
          "displayText": "Links to Other Platforms",
          "rawValueJson": "\"Links to Other Platforms\"",
          "numberFormat": "General"
        },
        {
          "row": 1,
          "column": 10,
          "displayText": "Have you joined our Discord? (https://discord.gg/B4Set59eKb)",
          "rawValueJson": "\"Have you joined our Discord? (https://discord.gg/B4Set59eKb)\"",
          "numberFormat": "General"
        },
        {
          "row": 1,
          "column": 11,
          "displayText": "Have you ever played on an SMP server?",
          "rawValueJson": "\"Have you ever played on an SMP server?\"",
          "numberFormat": "General"
        },
        {
          "row": 1,
          "column": 12,
          "displayText": "Have you ever created a Minecraft let's play series?",
          "rawValueJson": "\"Have you ever created a Minecraft let's play series?\"",
          "numberFormat": "General"
        },
        {
          "row": 1,
          "column": 13,
          "displayText": "Link us one video of yours that you are most proud of. Why is it your favorite?",
          "rawValueJson": "\"Link us one video of yours that you are most proud of. Why is it your favorite?\"",
          "numberFormat": "General"
        },
        {
          "row": 1,
          "column": 14,
          "displayText": "What kind of playstyle would you bring to AutoCraft SMP?",
          "rawValueJson": "\"What kind of playstyle would you bring to AutoCraft SMP?\"",
          "numberFormat": "General"
        },
        {
          "row": 1,
          "column": 15,
          "displayText": "What kind of builds would you add to AutoCraft SMP?",
          "rawValueJson": "\"What kind of builds would you add to AutoCraft SMP?\"",
          "numberFormat": "General"
        },
        {
          "row": 1,
          "column": 16,
          "displayText": "What kind of content would you create on AutoCraft SMP?",
          "rawValueJson": "\"What kind of content would you create on AutoCraft SMP?\"",
          "numberFormat": "General"
        },
        {
          "row": 1,
          "column": 17,
          "displayText": "There is always something happening on the server!\nWhat are you interested in being a part of?",
          "rawValueJson": "\"There is always something happening on the server!\\nWhat are you interested in being a part of?\"",
          "numberFormat": "General"
        },
        {
          "row": 1,
          "column": 18,
          "displayText": "Build Screenshots",
          "rawValueJson": "\"Build Screenshots\"",
          "numberFormat": "General"
        },
        {
          "row": 1,
          "column": 19,
          "displayText": "Is there anything else you would like to add to your AutoCraft SMP application?",
          "rawValueJson": "\"Is there anything else you would like to add to your AutoCraft SMP application?\"",
          "numberFormat": "General"
        },
        {
          "row": 2,
          "column": 1,
          "displayText": "5/16/2024 7:28:38",
          "rawValueJson": "45428.3115527662",
          "numberFormat": "m/d/yyyy h:mm:ss"
        },
        {
          "row": 2,
          "column": 6,
          "displayText": "He/Him/His",
          "rawValueJson": "\"He/Him/His\"",
          "numberFormat": "General"
        },
        {
          "row": 2,
          "column": 7,
          "displayText": "25",
          "rawValueJson": "25",
          "numberFormat": "General"
        },
        {
          "row": 2,
          "column": 10,
          "displayText": "Yes",
          "rawValueJson": "\"Yes\"",
          "numberFormat": "General"
        },
        {
          "row": 2,
          "column": 11,
          "displayText": "Yes",
          "rawValueJson": "\"Yes\"",
          "numberFormat": "General"
        },
        {
          "row": 2,
          "column": 12,
          "displayText": "Yes",
          "rawValueJson": "\"Yes\"",
          "numberFormat": "General"
        },
        {
          "row": 2,
          "column": 14,
          "displayText": "Definitely a builder. But I love an adventure!",
          "rawValueJson": "\"Definitely a builder. But I love an adventure!\"",
          "numberFormat": "General"
        },
        {
          "row": 2,
          "column": 15,
          "displayText": "Oh I got this awesome abandoned themepark/fair idea that has been in my head and creative world that I would absolutely love to make a reality!",
          "rawValueJson": "\"Oh I got this awesome abandoned themepark/fair idea that has been in my head and creative world that I would absolutely love to make a reality!\"",
          "numberFormat": "General"
        },
        {
          "row": 2,
          "column": 16,
          "displayText": "Definitely building focussed, but I am also big on collaboration and adventures. Meeting new people and making new memories.",
          "rawValueJson": "\"Definitely building focussed, but I am also big on collaboration and adventures. Meeting new people and making new memories.\"",
          "numberFormat": "General"
        },
        {
          "row": 2,
          "column": 17,
          "displayText": "Build Collaborations, Storyline Collaborations, Stream Days, Discord Events, Server Meetings",
          "rawValueJson": "\"Build Collaborations, Storyline Collaborations, Stream Days, Discord Events, Server Meetings\"",
          "numberFormat": "General"
        },
        {
          "row": 2,
          "column": 19,
          "displayText": "Not really I hope I can join you all in the amazing new memories of Season 5 of Autocraft",
          "rawValueJson": "\"Not really I hope I can join you all in the amazing new memories of Season 5 of Autocraft\"",
          "numberFormat": "General"
        },
        {
          "row": 3,
          "column": 1,
          "displayText": "5/16/2024 10:40:01",
          "rawValueJson": "45428.44445930555",
          "numberFormat": "m/d/yyyy h:mm:ss"
        },
        {
          "row": 3,
          "column": 6,
          "displayText": "He/Him/His",
          "rawValueJson": "\"He/Him/His\"",
          "numberFormat": "General"
        },
        {
          "row": 3,
          "column": 7,
          "displayText": "I would like to keep that private plz",
          "rawValueJson": "\"I would like to keep that private plz\"",
          "numberFormat": "General"
        },
        {
          "row": 3,
          "column": 10,
          "displayText": "Yes",
          "rawValueJson": "\"Yes\"",
          "numberFormat": "General"
        },
        {
          "row": 3,
          "column": 11,
          "displayText": "Yes",
          "rawValueJson": "\"Yes\"",
          "numberFormat": "General"
        },
        {
          "row": 3,
          "column": 12,
          "displayText": "No",
          "rawValueJson": "\"No\"",
          "numberFormat": "General"
        },
        {
          "row": 3,
          "column": 14,
          "displayText": "I would consider myself a builder and I'm not sure if this is what you are asking but im also just someone who likes to have have fun messing around.",
          "rawValueJson": "\"I would consider myself a builder and I'm not sure if this is what you are asking but im also just someone who likes to have have fun messing around.\"",
          "numberFormat": "General"
        },
        {
          "row": 3,
          "column": 15,
          "displayText": "I was thinking if I joined Auto Crafters I would maybe build a Big Mushroom Village Bigger than anything I've ever built before",
          "rawValueJson": "\"I was thinking if I joined Auto Crafters I would maybe build a Big Mushroom Village Bigger than anything I've ever built before\"",
          "numberFormat": "General"
        },
        {
          "row": 3,
          "column": 16,
          "displayText": "If I join Auto Crafters, I plan to still make Kingcraft content. And as for videos I would release on the auto crafters It would probably be Getting to know you guys working on my base And Shenanigans\\interactions",
          "rawValueJson": "\"If I join Auto Crafters, I plan to still make Kingcraft content. And as for videos I would release on the auto crafters It would probably be Getting to know you guys working on my base And Shenanigans\\\\interactions\"",
          "numberFormat": "General"
        },
        {
          "row": 3,
          "column": 17,
          "displayText": "Build Collaborations, Storyline Collaborations, Server Meetings",
          "rawValueJson": "\"Build Collaborations, Storyline Collaborations, Server Meetings\"",
          "numberFormat": "General"
        },
        {
          "row": 4,
          "column": 1,
          "displayText": "5/16/2024 17:58:49",
          "rawValueJson": "45428.74918337963",
          "numberFormat": "m/d/yyyy h:mm:ss"
        },
        {
          "row": 4,
          "column": 6,
          "displayText": "She/Her/Hers",
          "rawValueJson": "\"She/Her/Hers\"",
          "numberFormat": "General"
        },
        {
          "row": 4,
          "column": 7,
          "displayText": "21",
          "rawValueJson": "21",
          "numberFormat": "General"
        },
        {
          "row": 4,
          "column": 10,
          "displayText": "Yes",
          "rawValueJson": "\"Yes\"",
          "numberFormat": "General"
        },
        {
          "row": 4,
          "column": 11,
          "displayText": "Yes",
          "rawValueJson": "\"Yes\"",
          "numberFormat": "General"
        },
        {
          "row": 4,
          "column": 12,
          "displayText": "No",
          "rawValueJson": "\"No\"",
          "numberFormat": "General"
        },
        {
          "row": 4,
          "column": 14,
          "displayText": "Builder ",
          "rawValueJson": "\"Builder \"",
          "numberFormat": "General"
        },
        {
          "row": 4,
          "column": 15,
          "displayText": "Huge buildings I can try for my base and shops ",
          "rawValueJson": "\"Huge buildings I can try for my base and shops \"",
          "numberFormat": "General"
        },
        {
          "row": 4,
          "column": 16,
          "displayText": "I don’t know ",
          "rawValueJson": "\"I don’t know \"",
          "numberFormat": "General"
        },
        {
          "row": 4,
          "column": 17,
          "displayText": "Build Collaborations, Stream Days, Discord Events, Server Meetings",
          "rawValueJson": "\"Build Collaborations, Stream Days, Discord Events, Server Meetings\"",
          "numberFormat": "General"
        },
        {
          "row": 4,
          "column": 19,
          "displayText": "👆🏻 up to the Build Screenshots that’s is an old build from me and my dad build from another server ",
          "rawValueJson": "\"👆🏻 up to the Build Screenshots that’s is an old build from me and my dad build from another server \"",
          "numberFormat": "General"
        },
        {
          "row": 5,
          "column": 1,
          "displayText": "5/16/2024 19:08:01",
          "rawValueJson": "45428.79723232639",
          "numberFormat": "m/d/yyyy h:mm:ss"
        },
        {
          "row": 5,
          "column": 6,
          "displayText": "He/Him/His, They/Them/Theirs",
          "rawValueJson": "\"He/Him/His, They/Them/Theirs\"",
          "numberFormat": "General"
        },
        {
          "row": 5,
          "column": 7,
          "displayText": "35",
          "rawValueJson": "35",
          "numberFormat": "General"
        },
        {
          "row": 5,
          "column": 10,
          "displayText": "Yes",
          "rawValueJson": "\"Yes\"",
          "numberFormat": "General"
        },
        {
          "row": 5,
          "column": 11,
          "displayText": "Yes",
          "rawValueJson": "\"Yes\"",
          "numberFormat": "General"
        },
        {
          "row": 5,
          "column": 12,
          "displayText": "Yes",
          "rawValueJson": "\"Yes\"",
          "numberFormat": "General"
        },
        {
          "row": 5,
          "column": 14,
          "displayText": "Builder mainly but a bit of an explorer sometimes",
          "rawValueJson": "\"Builder mainly but a bit of an explorer sometimes\"",
          "numberFormat": "General"
        },
        {
          "row": 5,
          "column": 15,
          "displayText": "Base - Thinking of a few ideas maybe a fantasy/medivel or a whimsical build. Though there is a water base I've been wanting to do for a while\nShop - Maybe a stone shop or my personal favorite amethyst shop would be fun",
          "rawValueJson": "\"Base - Thinking of a few ideas maybe a fantasy/medivel or a whimsical build. Though there is a water base I've been wanting to do for a while\\nShop - Maybe a stone shop or my personal favorite amethyst shop would be fun\"",
          "numberFormat": "General"
        },
        {
          "row": 5,
          "column": 16,
          "displayText": "Weekly Let's play videos. Occasional shorts/tik toks, and weekly streams",
          "rawValueJson": "\"Weekly Let's play videos. Occasional shorts/tik toks, and weekly streams\"",
          "numberFormat": "General"
        },
        {
          "row": 5,
          "column": 17,
          "displayText": "Build Collaborations, Storyline Collaborations, Stream Days, Discord Events, Server Meetings",
          "rawValueJson": "\"Build Collaborations, Storyline Collaborations, Stream Days, Discord Events, Server Meetings\"",
          "numberFormat": "General"
        },
        {
          "row": 5,
          "column": 19,
          "displayText": "As stated before I've been a few SMPs before including - GrowthSMP, AzureSMP, PixieSMP and SovereignSMP. While I do have a set schedule for streams and my videos, I can be pretty flexible. I can be a bit on the reserved side at first but after you get to know me and especially if you get me on a topic I like, I may talk your ear off. I do like to try to change my skin for occasions whether the holidays or to fit my build or events as well. ",
          "rawValueJson": "\"As stated before I've been a few SMPs before including - GrowthSMP, AzureSMP, PixieSMP and SovereignSMP. While I do have a set schedule for streams and my videos, I can be pretty flexible. I can be a bit on the reserved side at first but after you get to know me and especially if you get me on a topic I like, I may talk your ear off. I do like to try to change my skin for occasions whether the holidays or to fit my build or events as well. \"",
          "numberFormat": "General"
        },
        {
          "row": 6,
          "column": 1,
          "displayText": "5/17/2024 10:20:44",
          "rawValueJson": "45429.43106231482",
          "numberFormat": "m/d/yyyy h:mm:ss"
        },
        {
          "row": 6,
          "column": 6,
          "displayText": "He/Him/His",
          "rawValueJson": "\"He/Him/His\"",
          "numberFormat": "General"
        },
        {
          "row": 6,
          "column": 7,
          "displayText": "21",
          "rawValueJson": "21",
          "numberFormat": "General"
        },
        {
          "row": 6,
          "column": 10,
          "displayText": "Yes",
          "rawValueJson": "\"Yes\"",
          "numberFormat": "General"
        },
        {
          "row": 6,
          "column": 11,
          "displayText": "Yes",
          "rawValueJson": "\"Yes\"",
          "numberFormat": "General"
        },
        {
          "row": 6,
          "column": 12,
          "displayText": "Yes",
          "rawValueJson": "\"Yes\"",
          "numberFormat": "General"
        },
        {
          "row": 6,
          "column": 14,
          "displayText": "I'm very much primarily into automatic farms, in some cases designing my own. Recently, though I have been getting more into building, working on more larger scale stuff.",
          "rawValueJson": "\"I'm very much primarily into automatic farms, in some cases designing my own. Recently, though I have been getting more into building, working on more larger scale stuff.\"",
          "numberFormat": "General"
        },
        {
          "row": 6,
          "column": 15,
          "displayText": "I'd like to revisit and expand on an old build of mine I called 'skylab'. It was essentially a big quartz disc over an ocean with some buildings. For 2.0 I'd probably add in more discs. perhaps built over a guardian farm. I have quite a geometric/futuristic build style so whatever I end up doing it's likely gonna feature lots of patterns and straight edges. As for shops, pretty much if I farm something I'll likely see if I can make a shop for it.  ",
          "rawValueJson": "\"I'd like to revisit and expand on an old build of mine I called 'skylab'. It was essentially a big quartz disc over an ocean with some buildings. For 2.0 I'd probably add in more discs. perhaps built over a guardian farm. I have quite a geometric/futuristic build style so whatever I end up doing it's likely gonna feature lots of patterns and straight edges. As for shops, pretty much if I farm something I'll likely see if I can make a shop for it.  \"",
          "numberFormat": "General"
        },
        {
          "row": 6,
          "column": 16,
          "displayText": "I's release just simple let's play videos every couple weeks or so. Similar to what I'm doing already with the Inter Realms SMP, alternating between servers for each video. I'm not much of a storyteller/lore person; I like to just show stuff as it is.",
          "rawValueJson": "\"I's release just simple let's play videos every couple weeks or so. Similar to what I'm doing already with the Inter Realms SMP, alternating between servers for each video. I'm not much of a storyteller/lore person; I like to just show stuff as it is.\"",
          "numberFormat": "General"
        },
        {
          "row": 6,
          "column": 17,
          "displayText": "Build Collaborations, Stream Days, Discord Events, Server Meetings",
          "rawValueJson": "\"Build Collaborations, Stream Days, Discord Events, Server Meetings\"",
          "numberFormat": "General"
        },
        {
          "row": 6,
          "column": 19,
          "displayText": "I've mentioned it above but I do also play on and make content from the Inter Realms SMP. I would be aiming to split my content evenly between the two servers but naturally there may be some sway one way or the other depending workload, events etc.",
          "rawValueJson": "\"I've mentioned it above but I do also play on and make content from the Inter Realms SMP. I would be aiming to split my content evenly between the two servers but naturally there may be some sway one way or the other depending workload, events etc.\"",
          "numberFormat": "General"
        }
      ]
    },
    "sampledLines": null,
    "samplingScheme": 0,
    "H_": {
      "T_": "AugLoop_ExcelTableAi_ExcelRecognizedTableNew",
      "B_": [
        "AugLoop_Excel_ExcelRangeWrapperAnnotation",
        "AugLoop_Core_Annotation"
      ]
    },
    "id": "f7d02d90-d241-414b-a3b4-f782e62de12a",
    "ownerId": "ExcelTableRecognitionReducer",
    "M_": {
      "state": 20
    }
  }
]