[
  {
    "range": {
      "worksheetId": "{C7A2D25A-DD25-4862-A9F2-51A8755CA501}",
      "top": 1,
      "left": 1,
      "bottom": 6,
      "right": 2
    },
    "interpretations": [
      {
        "confidence": 1,
        "location": {
          "worksheetId": "{C7A2D25A-DD25-4862-A9F2-51A8755CA501}",
          "top": 1,
          "bottom": 6,
          "left": 1,
          "right": 2
        },
        "orientation": "columnMajor",
        "headerRowCount": 1,
        "headerColumnCount": 0,
        "fields": [
          {
            "classification": "dimension",
            "aggregations": [],
            "headerReferences": [],
            "isTextual": false
          },
          {
            "classification": "dimension",
            "aggregations": [],
            "headerReferences": [],
            "isTextual": false
          }
        ],
        "headerNames": [
          "\"Day\"",
          "\"Weather\""
        ],
        "sampleCellData": [
          {
            "row": 1,
            "column": 1,
            "displayText": "Day",
            "rawValueJson": "\"Day\"",
            "numberFormat": "General"
          },
          {
            "row": 1,
            "column": 2,
            "displayText": "Weather",
            "rawValueJson": "\"Weather\"",
            "numberFormat": "General"
          },
          {
            "row": 2,
            "column": 1,
            "displayText": "Monday",
            "rawValueJson": "\"Monday\"",
            "numberFormat": "General"
          },
          {
            "row": 2,
            "column": 2,
            "displayText": "Sunny",
            "rawValueJson": "\"Sunny\"",
            "numberFormat": "General"
          },
          {
            "row": 3,
            "column": 1,
            "displayText": "Tuesday",
            "rawValueJson": "\"Tuesday\"",
            "numberFormat": "General"
          },
          {
            "row": 3,
            "column": 2,
            "displayText": "Rainy",
            "rawValueJson": "\"Rainy\"",
            "numberFormat": "General"
          },
          {
            "row": 4,
            "column": 1,
            "displayText": "Wednesday",
            "rawValueJson": "\"Wednesday\"",
            "numberFormat": "General"
          },
          {
            "row": 4,
            "column": 2,
            "displayText": "Rainy",
            "rawValueJson": "\"Rainy\"",
            "numberFormat": "General"
          },
          {
            "row": 5,
            "column": 1,
            "displayText": "Thursday",
            "rawValueJson": "\"Thursday\"",
            "numberFormat": "General"
          },
          {
            "row": 5,
            "column": 2,
            "displayText": "Sunny",
            "rawValueJson": "\"Sunny\"",
            "numberFormat": "General"
          },
          {
            "row": 6,
            "column": 1,
            "displayText": "Friday",
            "rawValueJson": "\"Friday\"",
            "numberFormat": "General"
          },
          {
            "row": 6,
            "column": 2,
            "displayText": "Cloudy",
            "rawValueJson": "\"Cloudy\"",
            "numberFormat": "General"
          }
        ]
      }
    ],
    "tableName": "Table2",
    "hasMergedcells": false,
    "boundaryConfidence": 1,
    "sheetName": "Weather",
    "isDataSampled": false,
    "primaryTable": {
      "tableType": "columnMajorFlat",
      "hasTotalRow": false,
      "hasTotalColumn": false,
      "sampleCells": [
        {
          "row": 1,
          "column": 1,
          "displayText": "Day",
          "rawValueJson": "\"Day\"",
          "numberFormat": "General"
        },
        {
          "row": 1,
          "column": 2,
          "displayText": "Weather",
          "rawValueJson": "\"Weather\"",
          "numberFormat": "General"
        },
        {
          "row": 2,
          "column": 1,
          "displayText": "Monday",
          "rawValueJson": "\"Monday\"",
          "numberFormat": "General"
        },
        {
          "row": 2,
          "column": 2,
          "displayText": "Sunny",
          "rawValueJson": "\"Sunny\"",
          "numberFormat": "General"
        },
        {
          "row": 3,
          "column": 1,
          "displayText": "Tuesday",
          "rawValueJson": "\"Tuesday\"",
          "numberFormat": "General"
        },
        {
          "row": 3,
          "column": 2,
          "displayText": "Rainy",
          "rawValueJson": "\"Rainy\"",
          "numberFormat": "General"
        },
        {
          "row": 4,
          "column": 1,
          "displayText": "Wednesday",
          "rawValueJson": "\"Wednesday\"",
          "numberFormat": "General"
        },
        {
          "row": 4,
          "column": 2,
          "displayText": "Rainy",
          "rawValueJson": "\"Rainy\"",
          "numberFormat": "General"
        },
        {
          "row": 5,
          "column": 1,
          "displayText": "Thursday",
          "rawValueJson": "\"Thursday\"",
          "numberFormat": "General"
        },
        {
          "row": 5,
          "column": 2,
          "displayText": "Sunny",
          "rawValueJson": "\"Sunny\"",
          "numberFormat": "General"
        },
        {
          "row": 6,
          "column": 1,
          "displayText": "Friday",
          "rawValueJson": "\"Friday\"",
          "numberFormat": "General"
        },
        {
          "row": 6,
          "column": 2,
          "displayText": "Cloudy",
          "rawValueJson": "\"Cloudy\"",
          "numberFormat": "General"
        }
      ]
    },
    "sampledLines": null,
    "samplingScheme": 0,
    "H_": {
      "T_": "AugLoop_ExcelTableAi_ExcelRecognizedTableNew",
      "B_": [
        "AugLoop_Excel_ExcelRangeWrapperAnnotation",
        "AugLoop_Core_Annotation"
      ]
    },
    "id": "811094c6-7511-442d-ab3d-5367999c21d1",
    "ownerId": "ExcelTableRecognitionReducer",
    "M_": {
      "state": 20
    }
  }
]