[
  {
    "range": {
      "worksheetId": "{BE94B338-FF81-4CD3-9AA1-C95192DB0E7B}",
      "top": 1,
      "left": 1,
      "bottom": 17,
      "right": 1
    },
    "interpretations": [
      {
        "confidence": 1,
        "location": {
          "worksheetId": "{BE94B338-FF81-4CD3-9AA1-C95192DB0E7B}",
          "top": 1,
          "bottom": 17,
          "left": 1,
          "right": 1
        },
        "orientation": "columnMajor",
        "headerRowCount": 1,
        "headerColumnCount": 0,
        "fields": [
          {
            "classification": "measure",
            "aggregations": [
              "sum"
            ],
            "headerReferences": [],
            "isTextual": false
          }
        ],
        "headerNames": [
          "\"Votes\""
        ],
        "sampleCellData": [
          {
            "row": 1,
            "column": 1,
            "displayText": "Votes",
            "rawValueJson": "\"Votes\"",
            "numberFormat": "General"
          },
          {
            "row": 2,
            "column": 1,
            "displayText": "0",
            "rawValueJson": "0",
            "numberFormat": "General"
          },
          {
            "row": 3,
            "column": 1,
            "displayText": "1",
            "rawValueJson": "1",
            "numberFormat": "General"
          },
          {
            "row": 4,
            "column": 1,
            "displayText": "299",
            "rawValueJson": "299",
            "numberFormat": "General"
          },
          {
            "row": 5,
            "column": 1,
            "displayText": "300",
            "rawValueJson": "300",
            "numberFormat": "General"
          },
          {
            "row": 6,
            "column": 1,
            "displayText": "599",
            "rawValueJson": "599",
            "numberFormat": "General"
          }
        ]
      }
    ],
    "tableName": "Input",
    "hasMergedcells": false,
    "boundaryConfidence": 1,
    "sheetName": "Sheet1",
    "isDataSampled": false,
    "primaryTable": {
      "tableType": "columnMajorFlat",
      "hasTotalRow": false,
      "hasTotalColumn": false,
      "sampleCells": [
        {
          "row": 1,
          "column": 1,
          "displayText": "Votes",
          "rawValueJson": "\"Votes\"",
          "numberFormat": "General"
        },
        {
          "row": 2,
          "column": 1,
          "displayText": "0",
          "rawValueJson": "0",
          "numberFormat": "General"
        },
        {
          "row": 3,
          "column": 1,
          "displayText": "1",
          "rawValueJson": "1",
          "numberFormat": "General"
        },
        {
          "row": 4,
          "column": 1,
          "displayText": "299",
          "rawValueJson": "299",
          "numberFormat": "General"
        },
        {
          "row": 5,
          "column": 1,
          "displayText": "300",
          "rawValueJson": "300",
          "numberFormat": "General"
        },
        {
          "row": 6,
          "column": 1,
          "displayText": "599",
          "rawValueJson": "599",
          "numberFormat": "General"
        }
      ]
    },
    "sampledLines": null,
    "samplingScheme": 0,
    "H_": {
      "T_": "AugLoop_ExcelTableAi_ExcelRecognizedTableNew",
      "B_": [
        "AugLoop_Excel_ExcelRangeWrapperAnnotation",
        "AugLoop_Core_Annotation"
      ]
    },
    "id": "850a1c21-d846-4e54-accc-8e3e8e8ffaa6",
    "ownerId": "ExcelTableRecognitionReducer",
    "M_": {
      "state": 20
    }
  }
]